showcount/__init__.py
showcount-0.0.1.dist-info/LICENSE
showcount-0.0.1.dist-info/METADATA
showcount-0.0.1.dist-info/WHEEL
showcount-0.0.1.dist-info/top_level.txt
showcount-0.0.1.dist-info/RECORD
